rubion/__init__.py
rubion-0.0.1.dist-info/METADATA
rubion-0.0.1.dist-info/WHEEL
rubion-0.0.1.dist-info/top_level.txt
rubion-0.0.1.dist-info/RECORD
