Metadata-Version: 2.4
Name: rubion
Version: 0.0.1
Summary: Python library for Rubika Bot API
Home-page: https://github.com/untilloop/rubion
Author: Until Loop
Author-email: info.untilloop@gmail.com
Requires-Python: >=3.8
Dynamic: author
Dynamic: author-email
Dynamic: description
Dynamic: description-content-type
Dynamic: home-page
Dynamic: requires-python
Dynamic: summary
